python_odpt/__init__.py
python_odpt/api/__init__.py
python_odpt/api/default/__init__.py
python_odpt/api/default/airport_operations_get_airports.py
python_odpt/api/default/airport_terminal_operations_get_airport_terminals.py
python_odpt/api/default/bus_operation_get_buses.py
python_odpt/api/default/bus_timetable_operations_get_bus_timetables.py
python_odpt/api/default/busroute_pattern_fare_operations_get_busroute_pattern_fares.py
python_odpt/api/default/busroute_pattern_operations_get_busroute_patterns.py
python_odpt/api/default/busstop_pole_operations_get_busstop_poles.py
python_odpt/api/default/busstop_pole_timetable_operations_get_busstop_pole_timetables.py
python_odpt/api/default/calendar_operations_get_calendars.py
python_odpt/api/default/data_dump_operations_dump.py
python_odpt/api/default/data_retrieve_operations_retrieve.py
python_odpt/api/default/data_search_operations_search.py
python_odpt/api/default/files_operations_get_files.py
python_odpt/api/default/flight_information_arrival_operations_get_flight_information_arrivals.py
python_odpt/api/default/flight_information_departure_operations_get_flight_information_departures.py
python_odpt/api/default/flight_schedule_operations_get_flight_schedules.py
python_odpt/api/default/flight_status_operations_get_flight_statuses.py
python_odpt/api/default/operator_operations_get_operators.py
python_odpt/api/default/passenger_survey_operations_get_passenger_surveys.py
python_odpt/api/default/place_search_operations_search.py
python_odpt/api/default/rail_direction_operations_get_rail_directions.py
python_odpt/api/default/railway_fare_operations_get_railway_fares.py
python_odpt/api/default/railway_operations_get_railways.py
python_odpt/api/default/station_operations_get_stations.py
python_odpt/api/default/station_timetable_operations_get_station_timetables.py
python_odpt/api/default/train_information_operations_get_train_information.py
python_odpt/api/default/train_operations_get_trains.py
python_odpt-0.1.5.dist-info/LICENSE
python_odpt-0.1.5.dist-info/METADATA
python_odpt-0.1.5.dist-info/WHEEL
python_odpt-0.1.5.dist-info/RECORD
